Workbook
Name Customer: ecom_customer_data!$1:$1048576
Name Sales: ecom_sales_data!$1:$1048576
Name Slicer_Month: #N/A
Name Slicer_Product_Category: #N/A
Name Slicer_Year: #N/A

Sheet Pivot Table
A3: Sum of Sales Amount | C3: Marital Status | D3: Sum of Sales Amount | F3: State | G3: Sum of Sales Amount | I3: Sales Trend | J3: Sum of Sales Amount
A4: 580723.58 | C4: Divorced | D4: 136388.35 | F4: Minnesota | G4: 19803.14 | I4: 2023
C5: Married | D5: 163650.38 | F5: Colorado | G5: 20564.34 | I5: Sep | J5: 48242.84
A6: Sum of Profit | C6: Single | D6: 128343.89 | F6: Florida | G6: 22187.12 | I6: Oct | J6: 47659.89
A7: 226101.39 | C7: Widowed | D7: 152340.96 | F7: Michigan | G7: 23605.02 | I7: Nov | J7: 39699.72
C8: Grand Total | D8: 580723.58 | F8: Illinois | G8: 26630.54 | I8: Dec | J8: 53308.8
A9: Distinct Count of Customer ID | F9: Pennsylvania | G9: 35676.47 | I9: 2024
A10: 478 | F10: Ohio | G10: 38032.8 | I10: Jan | J10: 48170.46
F11: Texas | G11: 49479.32 | I11: Feb | J11: 39013.29
A12: Distinct Count of Order ID | C12: Gender | D12: Sum of Sales Amount | F12: New York | G12: 65480.21 | I12: Mar | J12: 48268.19
A13: 1496 | C13: Female | D13: 178308.98 | F13: California | G13: 130563.78 | I13: Apr | J13: 57915.43
C14: Male | D14: 204915.85 | F14: Grand Total | G14: 432022.74 | I14: May | J14: 48603.3
C15: Non-Binary | D15: 197498.75 | I15: Jun | J15: 49706.68
C16: Grand Total | D16: 580723.58 | I16: Jul | J16: 44322.62
F17: Supplier | G17: Sum of Sales Amount | I17: Aug | J17: 55812.36
F18: West LLC | G18: 54314.82 | I18: Grand Total | J18: 580723.58
C19: Product Category | D19: Sum of Sales Amount | F19: Cook, Hall and Miller | G19: 49615.15
C20: Clothing | D20: 121829.71 | F20: Reese LLC | G20: 43666.65
C21: Electronics | D21: 98568.35 | F21: Barker-Baker | G21: 41262.4
C22: Furniture | D22: 121116.75 | F22: Hamilton, Kirby and Taylor | G22: 40467.48
C23: Office Supplies | D23: 75220.8 | F23: Fernandez, Willis and Potter | G23: 39902.85
C24: Toys | D24: 163987.97 | F24: Anderson-Jackson | G24: 37784.2
C25: Grand Total | D25: 580723.58 | F25: Davis Group | G25: 34643.84
F26: Myers-Barber | G26: 33262.38
C27: Region | D27: Sum of Sales Amount | F27: Jackson, Stewart and Jenkins | G27: 31174.43
C28: Central | D28: 151610.82 | F28: Grand Total | G28: 406094.2
C29: East | D29: 165622.57
C30: South | D30: 72007.04
C31: West | D31: 191483.15
C32: Grand Total | D32: 580723.58

Sheet Dashboard

Sheet ecom_sales_data
A1: Order ID | B1: Customer ID | C1: Customer Name | D1: Gender | E1: state | F1: Region | G1: Marital Status | H1: Order Date | I1: Year | J1: Month | K1: Product ID | L1: Product Name | M1: Supplier Name | N1: Product Category | O1: Cost Price | P1: Unit Price | Q1: Quantity | R1: Discount | S1: Sales Amount | T1: Profit | V1: =SUM(sales_tab[Profit]) -> 226101.39
A2: 767836 | B2: 641583 | C2: =VLOOKUP(sales_tab[[#This Row],[Customer ID]],customer_tab[],2,FALSE) -> Lee Maddox | D2: =VLOOKUP(sales_tab[[#This Row],[Customer ID]],customer_tab[],9,FALSE) -> Male | E2: =VLOOKUP(sales_tab[[#This Row],[Customer ID]],customer_tab[],5,FALSE) -> Kentucky | F2: =VLOOKUP(sales_tab[[#This Row],[Customer ID]],customer_tab[],6,FALSE) -> South | G2: =VLOOKUP(sales_tab[[#This Row],[Customer ID]],customer_tab[],7,FALSE) -> Divorced | H2: 45240 | I2: =TEXT(sales_tab[[#This Row],[Order Date]],"YYYY") -> 2023 | J2: =TEXT(sales_tab[[#This Row],[Order Date]],"MMM") -> Nov | K2: 9614 | L2: =VLOOKUP(sales_tab[[#This Row],[Product ID]],product_tab[],2,FALSE) -> Table | M2: =VLOOKUP(sales_tab[[#This Row],[Product ID]],product_tab[],4,FALSE) -> Peters Ltd | N2: Furniture | O2: 193.8731 | P2: 129.47 | Q2: 3 | R2: 0.09 | S2: =sales_tab[[#This Row],[Unit Price]]*sales_tab[[#This Row],[Quantity]] -> 388.41 | T2: =sales_tab[[#This Row],[Sales Amount]]-sales_tab[[#This Row],[Cost Price]] -> 194.5369
A3: 466628 | B3: 785678 | C3: =VLOOKUP(sales_tab[[#This Row],[Customer ID]],customer_tab[],2,FALSE) -> Stephen Johnson | D3: =VLOOKUP(sales_tab[[#This Row],[Customer ID]],customer_tab[],9,FALSE) -> Female | E3: =VLOOKUP(sales_tab[[#This Row],[Customer ID]],customer_tab[],5,FALSE) -> Kentucky | F3: =VLOOKUP(sales_tab[[#This Row],[Customer ID]],customer_tab[],6,FALSE) -> South | G3: =VLOOKUP(sales_tab[[#This Row],[Customer ID]],customer_tab[],7,FALSE) -> Widowed | H3: 45287 | I3: =TEXT(sales_tab[[#This Row],[Order Date]],"YYYY") -> 2023 | J3: =TEXT(sales_tab[[#This Row],[Order Date]],"MMM") -> Dec | K3: 1440 | L3: =VLOOKUP(sales_tab[[#This Row],[Product ID]],product_tab[],2,FALSE) -> Action Figure | M3: =VLOOKUP(sales_tab[[#This Row],[Product ID]],product_tab[],4,FALSE) -> Barker-Baker | N3: Toys | O3: 771.724 | P3: 242.72 | Q3: 5 | R3: 0.11 | S3: =sales_tab[[#This Row],[Unit Price]]*sales_tab[[#This Row],[Quantity]] -> 1213.6 | T3: =sales_tab[[#This Row],[Sales Amount]]-sales_tab[[#This Row],[Cost Price]] -> 441.876
A4: 540903 | B4: 893776 | C4: =VLOOKUP(sales_tab[[#This Row],[Customer ID]],customer_tab[],2,FALSE) -> Mark Arnold | D4: =VLOOKUP(sales_tab[[#This Row],[Customer ID]],customer_tab[],9,FALSE) -> Female | E4: =VLOOKUP(sales_tab[[#This Row],[Customer ID]],customer_tab[],5,FALSE) -> California | F4: =VLOOKUP(sales_tab[[#This Row],[Customer ID]],customer_tab[],6,FALSE) -> West | G4: =VLOOKUP(sales_tab[[#This Row],[Customer ID]],customer_tab[],7,FALSE) -> Divorced | H4: 45523 | I4: =TEXT(sales_tab[[#This Row],[Order Date]],"YYYY") -> 2024 | J4: =TEXT(sales_tab[[#This Row],[Order Date]],"MMM") -> Aug | K4: 4889 | L4: =VLOOKUP(sales_tab[[#This Row],[Product ID]],product_tab[],2,FALSE) -> T-shirt | M4: =VLOOKUP(sales_tab[[#This Row],[Product ID]],product_tab[],4,FALSE) -> Davis Group | N4: Clothing | O4: 622.682 | P4: 165.76 | Q4: 5 | R4: 0.16 | S4: =sales_tab[[#This Row],[Unit Price]]*sales_tab[[#This Row],[Quantity]] -> 828.8 | T4: =sales_tab[[#This Row],[Sales Amount]]-sales_tab[[#This Row],[Cost Price]] -> 206.118
A5: 867362 | B5: 344700 | C5: =VLOOKUP(sales_tab[[#This Row],[Customer ID]],customer_tab[],2,FALSE) -> Andre Carter | D5: =VLOOKUP(sales_tab[[#This Row],[Customer ID]],customer_tab[],9,FALSE) -> Female | E5: =VLOOKUP(sales_tab[[#This Row],[Customer ID]],customer_tab[],5,FALSE) -> Florida | F5: =VLOOKUP(sales_tab[[#This Row],[Customer ID]],customer_tab[],6,FALSE) -> South | G5: =VLOOKUP(sales_tab[[#This Row],[Customer ID]],customer_tab[],7,FALSE) -> Single | H5: 45471 | I5: =TEXT(sales_tab[[#This Row],[Order Date]],"YYYY") -> 2024 | J5: =TEXT(sales_tab[[#This Row],[Order Date]],"MMM") -> Jun | K5: 7085 | L5: =VLOOKUP(sales_tab[[#This Row],[Product ID]],product_tab[],2,FALSE) -> Jacket | M5: =VLOOKUP(sales_tab[[#This Row],[Product ID]],product_tab[],4,FALSE) -> Myers-Barber | N5: Clothing | O5: 341.7957 | P5: 178.83 | Q5: 3 | R5: 0.07 | S5: =sales_tab[[#This Row],[Unit Price]]*sales_tab[[#This Row],[Quantity]] -> 536.49 | T5: =sales_tab[[#This Row],[Sales Amount]]-sales_tab[[#This Row],[Cost Price]] -> 194.6943
A6: 732167 | B6: 618203 | C6: =VLOOKUP(sales_tab[[#This Row],[Customer ID]],customer_tab[],2,FALSE) -> Meghan Holmes | D6: =VLOOKUP(sales_tab[[#This Row],[Customer ID]],customer_tab[],9,FALSE) -> Female | E6: =VLOOKUP(sales_tab[[#This Row],[Customer ID]],customer_tab[],5,FALSE) -> Florida | F6: =VLOOKUP(sales_tab[[#This Row],[Customer ID]],customer_tab[],6,FALSE) -> South | G6: =VLOOKUP(sales_tab[[#This Row],[Customer ID]],customer_tab[],7,FALSE) -> Single | H6: 45327 | I6: =TEXT(sales_tab[[#This Row],[Order Date]],"YYYY") -> 2024 | J6: =TEXT(sales_tab[[#This Row],[Order Date]],"MMM") -> Feb | K6: 4971 | L6: =VLOOKUP(sales_tab[[#This Row],[Product ID]],product_tab[],2,FALSE) -> Marker | M6: =VLOOKUP(sales_tab[[#This Row],[Product ID]],product_tab[],4,FALSE) -> Perez LLC | N6: Office Supplies | O6: 158.311 | P6: 63.66 | Q6: 3 | R6: 0.05 | S6: =sales_tab[[#This Row],[Unit Price]]*sales_tab[[#This Row],[Quantity]] -> 190.98 | T6: =sales_tab[[#This Row],[Sales Amount]]-sales_tab[[#This Row],[Cost Price]] -> 32.669
A7: 755997 | B7: 973891 | C7: =VLOOKUP(sales_tab[[#This Row],[Customer ID]],customer_tab[],2,FALSE) -> Alex Parker | D7: =VLOOKUP(sales_tab[[#This Row],[Customer ID]],customer_tab[],9,FALSE) -> Female | E7: =VLOOKUP(sales_tab[[#This Row],[Customer ID]],customer_tab[],5,FALSE) -> California | F7: =VLOOKUP(sales_tab[[#This Row],[Customer ID]],customer_tab[],6,FALSE) -> West | G7: =VLOOKUP(sales_tab[[#This Row],[Customer ID]],customer_tab[],7,FALSE) -> Single | H7: 45178 | I7: =TEXT(sales_tab[[#This Row],[Order Date]],"YYYY") -> 2023 | J7: =TEXT(sales_tab[[#This Row],[Order Date]],"MMM") -> Sep | K7: 5942 | L7: =VLOOKUP(sales_tab[[#This Row],[Product ID]],product_tab[],2,FALSE) -> Stapler | M7: =VLOOKUP(sales_tab[[#This Row],[Product ID]],product_tab[],4,FALSE) -> Jones-Henderson | N7: Office Supplies | O7: 22.8992 | P7: 12.83 | Q7: 4 | R7: 0.19 | S7: =sales_tab[[#This Row],[Unit Price]]*sales_tab[[#This Row],[Quantity]] -> 51.32 | T7: =sales_tab[[#This Row],[Sales Amount]]-sales_tab[[#This Row],[Cost Price]] -> 28.4208
A8: 870751 | B8: 599682 | C8: =VLOOKUP(sales_tab[[#This Row],[Customer ID]],customer_tab[],2,FALSE) -> Gina Little | D8: =VLOOKUP(sales_tab[[#This Row],[Customer ID]],customer_tab[],9,FALSE) -> Male | E8: =VLOOKUP(sales_tab[[#This Row],[Customer ID]],customer_tab[],5,FALSE) -> California | F8: =VLOOKUP(sales_tab[[#This Row],[Customer ID]],customer_tab[],6,FALSE) -> West | G8: =VLOOKUP(sales_tab[[#This Row],[Customer ID]],customer_tab[],7,FALSE) -> Divorced | H8: 45414 | I8: =TEXT(sales_tab[[#This Row],[Order Date]],"YYYY") -> 2024 | J8: =TEXT(sales_tab[[#This Row],[Order Date]],"MMM") -> May | K8: 2834 | L8: =VLOOKUP(sales_tab[[#This Row],[Product ID]],product_tab[],2,FALSE) -> Tablet | M8: =VLOOKUP(sales_tab[[#This Row],[Product ID]],product_tab[],4,FALSE) -> Anderson-Jackson | N8: Electronics | O8: 154.397 | P8: 222.26 | Q8: 1 | R8: 0.05 | S8: =sales_tab[[#This Row],[Unit Price]]*sales_tab[[#This Row],[Quantity]] -> 222.26 | T8: =sales_tab[[#This Row],[Sales Amount]]-sales_tab[[#This Row],[Cost Price]] -> 67.863
A9: 167125 | B9: 407527 | C9: =VLOOKUP(sales_tab[[#This Row],[Customer ID]],customer_tab[],2,FALSE) -> Heather Vargas | D9: =VLOOKUP(sales_tab[[#This Row],[Customer ID]],customer_tab[],9,FALSE) -> Non-Binary | E9: =VLOOKUP(sales_tab[[#This Row],[Customer ID]],customer_tab[],5,FALSE) -> California | F9: =VLOOKUP(sales_tab[[#This Row],[Customer ID]],customer_tab[],6,FALSE) -> West | G9: =VLOOKUP(sales_tab[[#This Row],[Customer ID]],customer_tab[],7,FALSE) -> Single | H9: 45434 | I9: =TEXT(sales_tab[[#This Row],[Order Date]],"YYYY") -> 2024 | J9: =TEXT(sales_tab[[#This Row],[Order Date]],"MMM") -> May | K9: 4541 | L9: =VLOOKUP(sales_tab[[#This Row],[Product ID]],product_tab[],2,FALSE) -> Pen | M9: =VLOOKUP(sales_tab[[#This Row],[Product ID]],product_tab[],4,FALSE) -> Mccall Inc | N9: Office Supplies | O9: 156.44 | P9: 69.5 | Q9: 3 | R9: 0.08 | S9: =sales_tab[[#This Row],[Unit Price]]*sales_tab[[#This Row],[Quantity]] -> 208.5 | T9: =sales_tab[[#This Row],[Sales Amount]]-sales_tab[[#This Row],[Cost Price]] -> 52.06
A10: 257856 | B10: 590702 | C10: =VLOOKUP(sales_tab[[#This Row],[Customer ID]],customer_tab[],2,FALSE) -> Brett Schroeder | D10: =VLOOKUP(sales_tab[[#This Row],[Customer ID]],customer_tab[],9,FALSE) -> Female | E10: =VLOOKUP(sales_tab[[#This Row],[Customer ID]],customer_tab[],5,FALSE) -> California | F10: =VLOOKUP(sales_tab[[#This Row],[Customer ID]],customer_tab[],6,FALSE) -> West | G10: =VLOOKUP(sales_tab[[#This Row],[Customer ID]],customer_tab[],7,FALSE) -> Married | H10: 45413 | I10: =TEXT(sales_tab[[#This Row],[Order Date]],"YYYY") -> 2024 | J10: =TEXT(sales_tab[[#This Row],[Order Date]],"MMM") -> May | K10: 1794 | L10: =VLOOKUP(sales_tab[[#This Row],[Product ID]],product_tab[],2,FALSE) -> Board Game | M10: =VLOOKUP(sales_tab[[#This Row],[Product ID]],product_tab[],4,FALSE) -> Reese LLC | N10: Toys | O10: 676.645 | P10: 210.95 | Q10: 5 | R10: 0.22 | S10: =sales_tab[[#This Row],[Unit Price]]*sales_tab[[#This Row],[Quantity]] -> 1054.75 | T10: =sales_tab[[#This Row],[Sales Amount]]-sales_tab[[#This Row],[Cost Price]] -> 378.105
A11: 277436 | B11: 453436 | C11: =VLOOKUP(sales_tab[[#This Row],[Customer ID]],customer_tab[],2,FALSE) -> Steven Huang | D11: =VLOOKUP(sales_tab[[#This Row],[Customer ID]],customer_tab[],9,FALSE) -> Male | E11: =VLOOKUP(sales_tab[[#This Row],[Customer ID]],customer_tab[],5,FALSE) -> California | F11: =VLOOKUP(sales_tab[[#This Row],[Customer ID]],customer_tab[],6,FALSE) -> West | G11: =VLOOKUP(sales_tab[[#This Row],[Customer ID]],customer_tab[],7,FALSE) -> Single | H11: 45235 | I11: =TEXT(sales_tab[[#This Row],[Order Date]],"YYYY") -> 2023 | J11: =TEXT(sales_tab[[#This Row],[Order Date]],"MMM") -> Nov | K11: 2034 | L11: =VLOOKUP(sales_tab[[#This Row],[Product ID]],product_tab[],2,FALSE) -> Camera | M11: =VLOOKUP(sales_tab[[#This Row],[Product ID]],product_tab[],4,FALSE) -> Johns and Sons | N11: Electronics | O11: 277.115 | P11: 70.85 | Q11: 5 | R11: 0.02 | S11: =sales_tab[[#This Row],[Unit Price]]*sales_tab[[#This Row],[Quantity]] -> 354.25 | T11: =sales_tab[[#This Row],[Sales Amount]]-sales_tab[[#This Row],[Cost Price]] -> 77.135
A12: 272962 | B12: 165946 | C12: =VLOOKUP(sales_tab[[#This Row],[Customer ID]],customer_tab[],2,FALSE) -> Brian Liu | D12: =VLOOKUP(sales_tab[[#This Row],[Customer ID]],customer_tab[],9,FALSE) -> Female | E12: =VLOOKUP(sales_tab[[#This Row],[Customer ID]],customer_tab[],5,FALSE) -> California | F12: =VLOOKUP(sales_tab[[#This Row],[Customer ID]],customer_tab[],6,FALSE) -> West | G12: =VLOOKUP(sales_tab[[#This Row],[Customer ID]],customer_tab[],7,FALSE) -> Single | H12: 45317 | I12: =TEXT(sales_tab[[#This Row],[Order Date]],"YYYY") -> 2024 | J12: =TEXT(sales_tab[[#This Row],[Order Date]],"MMM") -> Jan | K12: 6681 | L12: =VLOOKUP(sales_tab[[#This Row],[Product ID]],product_tab[],2,FALSE) -> Desk | M12: =VLOOKUP(sales_tab[[#This Row],[Product ID]],product_tab[],4,FALSE) -> Fernandez, Willis and Potter | N12: Furniture | O12: 584.0828 | P12: 204.63 | Q12: 4 | R12: 0.11 | S12: =sales_tab[[#This Row],[Unit Price]]*sales_tab[[#This Row],[Quantity]] -> 818.52 | T12: =sales_tab[[#This Row],[Sales Amount]]-sales_tab[[#This Row],[Cost Price]] -> 234.4372
A13: 190255 | B13: 815203 | C13: =VLOOKUP(sales_tab[[#This Row],[Customer ID]],customer_tab[],2,FALSE) -> Johnny Potter | D13: =VLOOKUP(sales_tab[[#This Row],[Customer ID]],customer_tab[],9,FALSE) -> Female | E13: =VLOOKUP(sales_tab[[#This Row],[Customer ID]],customer_tab[],5,FALSE) -> California | F13: =VLOOKUP(sales_tab[[#This Row],[Customer ID]],customer_tab[],6,FALSE) -> West | G13: =VLOOKUP(sales_tab[[#This Row],[Customer ID]],customer_tab[],7,FALSE) -> Widowed | H13: 45370 | I13: =TEXT(sales_tab[[#This Row],[Order Date]],"YYYY") -> 2024 | J13: =TEXT(sales_tab[[#This Row],[Order Date]],"MMM") -> Mar | K13: 3312 | L13: =VLOOKUP(sales_tab[[#This Row],[Product ID]],product_tab[],2,FALSE) -> Toy Car | M13: =VLOOKUP(sales_tab[[#This Row],[Product ID]],product_tab[],4,FALSE) -> West LLC | N13: Toys | O13: 1058.671 | P13: 287.38 | Q13: 5 | R13: 0.11 | S13: =sales_tab[[#This Row],[Unit Price]]*sales_tab[[#This Row],[Quantity]] -> 1436.9 | T13: =sales_tab[[#This Row],[Sales Amount]]-sales_tab[[#This Row],[Cost Price]] -> 378.229
... A1497: 617156 | B1497: 789562 | C1497: =VLOOKUP(sales_tab[[#This Row],[Customer ID]],customer_tab[],2,FALSE) -> Paul Craig | D1497: =VLOOKUP(sales_tab[[#This Row],[Customer ID]],customer_tab[],9,FALSE) -> Non-Binary | E1497: =VLOOKUP(sales_tab[[#This Row],[Customer ID]],customer_tab[],5,FALSE) -> Rhode Island | F1497: =VLOOKUP(sales_tab[[#This Row],[Customer ID]],customer_tab[],6,FALSE) -> East | G1497: =VLOOKUP(sales_tab[[#This Row],[Customer ID]],customer_tab[],7,FALSE) -> Widowed | H1497: 45348 | I1497: =TEXT(sales_tab[[#This Row],[Order Date]],"YYYY") -> 2024 | J1497: =TEXT(sales_tab[[#This Row],[Order Date]],"MMM") -> Feb | K1497: 6681 | L1497: =VLOOKUP(sales_tab[[#This Row],[Product ID]],product_tab[],2,FALSE) -> Desk | M1497: =VLOOKUP(sales_tab[[#This Row],[Product ID]],product_tab[],4,FALSE) -> Fernandez, Willis and Potter | N1497: Furniture | O1497: 364.1208 | P1497: 204.63 | Q1497: 4 | R1497: 0.21 | S1497: =sales_tab[[#This Row],[Unit Price]]*sales_tab[[#This Row],[Quantity]] -> 818.52 | T1497: =sales_tab[[#This Row],[Sales Amount]]-sales_tab[[#This Row],[Cost Price]] -> 454.3992

Sheet ecom_customer_data
A1: Customer ID | B1: Full Name | C1: Country | D1: City | E1: State | F1: Region | G1: Marital Status | H1: Age | I1: Gender
A2: 641583 | B2: Lee Maddox | C2: United States | D2: Henderson | E2: Kentucky | F2: South | G2: Divorced | H2: 24 | I2: Male
A3: 785678 | B3: Stephen Johnson | C3: United States | D3: Henderson | E3: Kentucky | F3: South | G3: Widowed | H3: 24 | I3: Female
A4: 893776 | B4: Mark Arnold | C4: United States | D4: Los Angeles | E4: California | F4: West | G4: Divorced | H4: 56 | I4: Female
A5: 344700 | B5: Andre Carter | C5: United States | D5: Fort Lauderdale | E5: Florida | F5: South | G5: Single | H5: 64 | I5: Female
A6: 618203 | B6: Meghan Holmes | C6: United States | D6: Fort Lauderdale | E6: Florida | F6: South | G6: Single | H6: 80 | I6: Female
A7: 973891 | B7: Alex Parker | C7: United States | D7: Los Angeles | E7: California | F7: West | G7: Single | H7: 53 | I7: Female
A8: 599682 | B8: Gina Little | C8: United States | D8: Los Angeles | E8: California | F8: West | G8: Divorced | H8: 54 | I8: Male
A9: 407527 | B9: Heather Vargas | C9: United States | D9: Los Angeles | E9: California | F9: West | G9: Single | H9: 20 | I9: Non-Binary
A10: 590702 | B10: Brett Schroeder | C10: United States | D10: Los Angeles | E10: California | F10: West | G10: Married | H10: 67 | I10: Female
A11: 453436 | B11: Steven Huang | C11: United States | D11: Los Angeles | E11: California | F11: West | G11: Single | H11: 72 | I11: Male
A12: 165946 | B12: Brian Liu | C12: United States | D12: Los Angeles | E12: California | F12: West | G12: Single | H12: 42 | I12: Female
A13: 815203 | B13: Johnny Potter | C13: United States | D13: Los Angeles | E13: California | F13: West | G13: Widowed | H13: 58 | I13: Female
... A479: 384192 | B479: Shannon Davis | C479: United States | D479: Pasadena | E479: Texas | F479: Central | G479: Single | H479: 26 | I479: Female

Sheet ecom_product_data
A1: Product ID | B1: Product Name | C1: Product Category | D1: Supplier | E1: Cost Price
A2: 8348 | B2: Laptop | C2: Electronics | D2: Jackson, Stewart and Jenkins | E2: =VLOOKUP(A2,ecom_sales_data!K2:O1497,3,0) -> Jackson, Stewart and Jenkins
A3: 6233 | B3: Smartphone | C3: Electronics | D3: Hensley-Pratt | E3: =VLOOKUP(A3,ecom_sales_data!K3:O1498,3,0) -> Hensley-Pratt
A4: 9251 | B4: Headphones | C4: Electronics | D4: Yates Group | E4: =VLOOKUP(A4,ecom_sales_data!K4:O1499,3,0) -> Yates Group
A5: 2034 | B5: Camera | C5: Electronics | D5: Johns and Sons | E5: =VLOOKUP(A5,ecom_sales_data!K5:O1500,3,0) -> Johns and Sons
A6: 2834 | B6: Tablet | C6: Electronics | D6: Anderson-Jackson | E6: =VLOOKUP(A6,ecom_sales_data!K6:O1501,3,0) -> Anderson-Jackson
A7: 6681 | B7: Desk | C7: Furniture | D7: Fernandez, Willis and Potter | E7: =VLOOKUP(A7,ecom_sales_data!K7:O1502,3,0) -> Fernandez, Willis and Potter
A8: 5842 | B8: Chair | C8: Furniture | D8: Cook, Hall and Miller | E8: =VLOOKUP(A8,ecom_sales_data!K8:O1503,3,0) -> Cook, Hall and Miller
A9: 2914 | B9: Bookshelf | C9: Furniture | D9: Davis-Ramirez | E9: =VLOOKUP(A9,ecom_sales_data!K9:O1504,3,0) -> Davis-Ramirez
A10: 9614 | B10: Table | C10: Furniture | D10: Peters Ltd | E10: =VLOOKUP(A10,ecom_sales_data!K10:O1505,3,0) -> Peters Ltd
A11: 2117 | B11: Sofa | C11: Furniture | D11: Holden Inc | E11: =VLOOKUP(A11,ecom_sales_data!K11:O1506,3,0) -> Holden Inc
A12: 4541 | B12: Pen | C12: Office Supplies | D12: Mccall Inc | E12: =VLOOKUP(A12,ecom_sales_data!K12:O1507,3,0) -> Mccall Inc
A13: 8522 | B13: Notebook | C13: Office Supplies | D13: Estrada LLC | E13: =VLOOKUP(A13,ecom_sales_data!K13:O1508,3,0) -> Estrada LLC
... A26: 3312 | B26: Toy Car | C26: Toys | D26: West LLC | E26: =VLOOKUP(A26,ecom_sales_data!K26:O1521,3,0) -> West LLC
